bpkit/__init__.py
bpkit/foo.py
bpkit-0.0.5.dist-info/METADATA
bpkit-0.0.5.dist-info/WHEEL
bpkit-0.0.5.dist-info/licenses/LICENSE
bpkit-0.0.5.dist-info/RECORD
