Metadata-Version: 2.4
Name: bpkit
Version: 0.0.5
Summary: Blueprint development kit for Python
Project-URL: Homepage, https://evgnomon.github.io/bpkit/
Project-URL: Repository, https://github.com/evgnomon/bpkit
Project-URL: Documentation, https://evgnomon.github.io/bpkit/
Author-email: Hamed Ghasemzadeh <hg@evgnomon.org>
License-File: LICENSE
Keywords: python
Classifier: Intended Audience :: Developers
Classifier: Programming Language :: Python
Classifier: Programming Language :: Python :: 3
Classifier: Programming Language :: Python :: 3.9
Classifier: Programming Language :: Python :: 3.10
Classifier: Programming Language :: Python :: 3.11
Classifier: Programming Language :: Python :: 3.12
Classifier: Programming Language :: Python :: 3.13
Classifier: Topic :: Software Development :: Libraries :: Python Modules
Requires-Python: <4.0,>=3.9
